onegov.notice-0.11.1-py3.6-nspkg.pth
onegov/notice/.gitignore
onegov/notice/__init__.py
onegov/notice/collections.py
onegov/notice/models.py
onegov/notice/upgrade.py
onegov/notice/tests/conftest.py
onegov/notice/tests/test_collections.py
onegov/notice/tests/test_models.py
onegov.notice-0.11.1.dist-info/METADATA
onegov.notice-0.11.1.dist-info/WHEEL
onegov.notice-0.11.1.dist-info/entry_points.txt
onegov.notice-0.11.1.dist-info/namespace_packages.txt
onegov.notice-0.11.1.dist-info/top_level.txt
onegov.notice-0.11.1.dist-info/RECORD
